wmidevicemanager/__init__.py
wmidevicemanager/const.py
wmidevicemanager/win32pnpentity.py
wmidevicemanager/wmidevicemanager.py
wmidevicemanager-1.2.3.dist-info/LICENSE
wmidevicemanager-1.2.3.dist-info/METADATA
wmidevicemanager-1.2.3.dist-info/WHEEL
wmidevicemanager-1.2.3.dist-info/top_level.txt
wmidevicemanager-1.2.3.dist-info/RECORD
