Metadata-Version: 2.1
Name: wmidevicemanager
Version: 1.2.3
Summary: A library to get information in device manager based on WMI.
Home-page: https://github.com/masamitsu-murase/wmi_device_manager
Author: Masamitsu MURASE
Author-email: masamitsu.murase@gmail.com
License: MIT
Project-URL: Bug Reports, https://github.com/masamitsu-murase/wmi_device_manager/issues
Project-URL: Source, https://github.com/masamitsu-murase/wmi_device_manager
Keywords: WMI device manager
Platform: UNKNOWN
Requires-Python: >=2.7, !=3.0.*, !=3.1.*, !=3.2.*, !=3.3.*, !=3.4.*, <4
Requires-Dist: comtypes
